[{"hour":0,"price":{"PCB":0.15164,"CYM":0.15164}},{"hour":1,"price":{"PCB":0.14108,"CYM":0.14108}},{"hour":2,"price":{"PCB":0.13841,"CYM":0.13841}},{"hour":3,"price":{"PCB":0.1336,"CYM":0.1336}},{"hour":4,"price":{"PCB":0.13106,"CYM":0.13106}},{"hour":5,"price":{"PCB":0.132,"CYM":0.132}},{"hour":6,"price":{"PCB":0.13153,"CYM":0.13153}},{"hour":7,"price":{"PCB":0.13044,"CYM":0.13044}},{"hour":8,"price":{"PCB":0.1269,"CYM":0.1269}},{"hour":9,"price":{"PCB":0.10066,"CYM":0.10066}},{"hour":10,"price":{"PCB":0.06385,"CYM":0.06385}},{"hour":11,"price":{"PCB":0.05432,"CYM":0.05432}},{"hour":12,"price":{"PCB":0.05435,"CYM":0.05435}},{"hour":13,"price":{"PCB":0.053869999999999994,"CYM":0.053869999999999994}},{"hour":14,"price":{"PCB":0.054090000000000006,"CYM":0.054090000000000006}},{"hour":15,"price":{"PCB":0.03933,"CYM":0.03933}},{"hour":16,"price":{"PCB":0.03429,"CYM":0.03429}},{"hour":17,"price":{"PCB":0.03686,"CYM":0.03686}},{"hour":18,"price":{"PCB":0.061380000000000004,"CYM":0.061380000000000004}},{"hour":19,"price":{"PCB":0.11757,"CYM":0.11757}},{"hour":20,"price":{"PCB":0.14669,"CYM":0.14669}},{"hour":21,"price":{"PCB":0.15483000000000002,"CYM":0.15483000000000002}},{"hour":22,"price":{"PCB":0.16036,"CYM":0.16036}},{"hour":23,"price":{"PCB":0.14659,"CYM":0.14659}}]