[{"hour":0,"price":{"PCB":0.15325,"CYM":0.15325}},{"hour":1,"price":{"PCB":0.14615,"CYM":0.14615}},{"hour":2,"price":{"PCB":0.12943000000000002,"CYM":0.12943000000000002}},{"hour":3,"price":{"PCB":0.12078,"CYM":0.12078}},{"hour":4,"price":{"PCB":0.12029000000000001,"CYM":0.12029000000000001}},{"hour":5,"price":{"PCB":0.11986,"CYM":0.11986}},{"hour":6,"price":{"PCB":0.12064,"CYM":0.12064}},{"hour":7,"price":{"PCB":0.11915,"CYM":0.11915}},{"hour":8,"price":{"PCB":0.11903,"CYM":0.11903}},{"hour":9,"price":{"PCB":0.111,"CYM":0.111}},{"hour":10,"price":{"PCB":0.08386,"CYM":0.08386}},{"hour":11,"price":{"PCB":0.05043,"CYM":0.05043}},{"hour":12,"price":{"PCB":0.03282,"CYM":0.03282}},{"hour":13,"price":{"PCB":0.03032,"CYM":0.03032}},{"hour":14,"price":{"PCB":0.03058,"CYM":0.03058}},{"hour":15,"price":{"PCB":0.03116,"CYM":0.03116}},{"hour":16,"price":{"PCB":0.03182,"CYM":0.03182}},{"hour":17,"price":{"PCB":0.03272,"CYM":0.03272}},{"hour":18,"price":{"PCB":0.08101,"CYM":0.08101}},{"hour":19,"price":{"PCB":0.12637,"CYM":0.12637}},{"hour":20,"price":{"PCB":0.16269999999999998,"CYM":0.16269999999999998}},{"hour":21,"price":{"PCB":0.15841,"CYM":0.15841}},{"hour":22,"price":{"PCB":0.15037999999999999,"CYM":0.15037999999999999}},{"hour":23,"price":{"PCB":0.13998,"CYM":0.13998}}]