[{"hour":0,"price":{"PCB":0.16577,"CYM":0.16577}},{"hour":1,"price":{"PCB":0.16624,"CYM":0.16624}},{"hour":2,"price":{"PCB":0.1611,"CYM":0.1611}},{"hour":3,"price":{"PCB":0.16805,"CYM":0.16805}},{"hour":4,"price":{"PCB":0.16749,"CYM":0.16749}},{"hour":5,"price":{"PCB":0.15959,"CYM":0.15959}},{"hour":6,"price":{"PCB":0.15555000000000002,"CYM":0.15555000000000002}},{"hour":7,"price":{"PCB":0.16013999999999998,"CYM":0.16013999999999998}},{"hour":8,"price":{"PCB":0.15088,"CYM":0.15088}},{"hour":9,"price":{"PCB":0.13898,"CYM":0.13898}},{"hour":10,"price":{"PCB":0.12267,"CYM":0.12267}},{"hour":11,"price":{"PCB":0.10179,"CYM":0.10179}},{"hour":12,"price":{"PCB":0.0696,"CYM":0.0696}},{"hour":13,"price":{"PCB":0.08331999999999999,"CYM":0.08331999999999999}},{"hour":14,"price":{"PCB":0.06644,"CYM":0.06644}},{"hour":15,"price":{"PCB":0.08578,"CYM":0.08578}},{"hour":16,"price":{"PCB":0.11735,"CYM":0.11735}},{"hour":17,"price":{"PCB":0.12735,"CYM":0.12735}},{"hour":18,"price":{"PCB":0.152,"CYM":0.152}},{"hour":19,"price":{"PCB":0.16956,"CYM":0.16956}},{"hour":20,"price":{"PCB":0.1869,"CYM":0.1869}},{"hour":21,"price":{"PCB":0.19279,"CYM":0.19279}},{"hour":22,"price":{"PCB":0.17311,"CYM":0.17311}},{"hour":23,"price":{"PCB":0.16795,"CYM":0.16795}}]